{"word2id": {"PAD": 0, "DUMMY_TASK": 1, "ac": 2, "sink": 3, "hboard": 4, "cabinets": 5, "closer": 6, "sheet": 7, "system": 8, "electrode": 9, "detector": 10, "fm900": 11, "member": 12, "tv": 13, "heads": 14, "of": 15, "coved": 16, "doors": 17, "corner": 18, "paint": 19, "electrical": 20, "apply": 21, "type": 22, "2": 23, "gypsum": 24, "frp": 25, "installation": 26, "lighting": 27, "wiring": 28, "conduits": 29, "homogeneous": 30, "activated": 31, "space": 32, "flush": 33, "firecut": 34, "pretreatment": 35, "lightings": 36, "punching": 37, "cladding": 38, "battery": 39, "frame": 40, "cabinet": 41, "3d": 42, "filters": 43, "panel": 44, "couplings": 45, "accessories": 46, "for": 47, "iron": 48, "filler": 49, "tiles": 50, "emulsion": 51, "tie": 52, "runners": 53, "2d": 54, "purlins": 55, "label": 56, "butt": 57, "skeleton": 58, "windows": 59, "trunking": 60, "finsishes": 61, "wire": 62, "grilles": 63, "tray": 64, "antimould": 65, "interface": 66, "fan": 67, "pipe": 68, "channel": 69, "timber": 70, "conduit": 71, "bondek": 72, "chamber": 73, "detectors": 74, "corrugated": 75, "elastometric": 76, "metal": 77, "weather": 78, "shear": 79, "beam": 80, "rubber": 81, "candleloc": 82, "nonarmoured": 83, "wall": 84, "mineral": 85, "composite": 86, "window": 87, "steel": 88, "column": 89, "vinyl": 90, "nonslip": 91, "tile": 92, "aluminium": 93, "room": 94, "stud": 95, "braces": 96, "chair": 97, "solid": 98, "nonfrp": 99, "layer": 100, "flexible": 101, "coat": 102, "threshold": 103, "skirting": 104, "spring": 105, "ventilation": 106, "grooved": 107, "air": 108, "waterproofing": 109, "condiuts": 110, "knauf": 111, "glass": 112, "finishings": 113, "hinge": 114, "porcelain": 115, "floor": 116, "hardwood": 117, "plane": 118, "mep": 119, "diffuser": 120, "acoustic": 121, "fire": 122, "vibration": 123, "strucutral": 124, "lysaght": 125, "casting": 126, "grout": 127, "sprinkler": 128, "wool": 129, "track": 130, "amoured": 131, "bells": 132, "addings": 133, "isolators": 134, "assembly": 135, "toiletsink": 136, "board": 137, "concrete": 138, "promatect": 139, "pvc": 140, "overhead": 141, "swa": 142, "with": 143, "latches": 144, "welding": 145, "carbon": 146, "busbar": 147, "coated": 148, "smoke": 149, "toilet": 150, "upvc": 151, "pipes": 152, "handle": 153, "contains": 154, "surface": 155, "rockwool": 156, "cast": 157, "belongsto": 158, "painting": 159, "laminate": 160, "ceiling": 161, "door": 162, "galvanized": 163, "infill": 164, "rebar": 165, "ironmongery": 166, "laminates": 167, "cement": 168, "and": 169, "filter": 170, "bar": 171, "epoxy": 172, "core": 173, "noggins": 174, "at": 175, "fillet": 176, "mixture": 177, "fittings": 178, "none": 179, "pencil": 180, "fixing": 181, "reinforcement": 182, "cable": 183, "nonshrink": 184, "copper": 185, "spacer": 186, "rod": 187, "profile": 188, "weld": 189, "slab": 190, "pouring": 191, "angle": 192, "membrane": 193, "parttern": 194, "gemtree": 195, "insulation": 196, "cemenititious": 197, "alarm": 198, "protection": 199, "constrains": 200}, "id2word": {"0": "PAD", "1": "DUMMY_TASK", "2": "ac", "3": "sink", "4": "hboard", "5": "cabinets", "6": "closer", "7": "sheet", "8": "system", "9": "electrode", "10": "detector", "11": "fm900", "12": "member", "13": "tv", "14": "heads", "15": "of", "16": "coved", "17": "doors", "18": "corner", "19": "paint", "20": "electrical", "21": "apply", "22": "type", "23": "2", "24": "gypsum", "25": "frp", "26": "installation", "27": "lighting", "28": "wiring", "29": "conduits", "30": "homogeneous", "31": "activated", "32": "space", "33": "flush", "34": "firecut", "35": "pretreatment", "36": "lightings", "37": "punching", "38": "cladding", "39": "battery", "40": "frame", "41": "cabinet", "42": "3d", "43": "filters", "44": "panel", "45": "couplings", "46": "accessories", "47": "for", "48": "iron", "49": "filler", "50": "tiles", "51": "emulsion", "52": "tie", "53": "runners", "54": "2d", "55": "purlins", "56": "label", "57": "butt", "58": "skeleton", "59": "windows", "60": "trunking", "61": "finsishes", "62": "wire", "63": "grilles", "64": "tray", "65": "antimould", "66": "interface", "67": "fan", "68": "pipe", "69": "channel", "70": "timber", "71": "conduit", "72": "bondek", "73": "chamber", "74": "detectors", "75": "corrugated", "76": "elastometric", "77": "metal", "78": "weather", "79": "shear", "80": "beam", "81": "rubber", "82": "candleloc", "83": "nonarmoured", "84": "wall", "85": "mineral", "86": "composite", "87": "window", "88": "steel", "89": "column", "90": "vinyl", "91": "nonslip", "92": "tile", "93": "aluminium", "94": "room", "95": "stud", "96": "braces", "97": "chair", "98": "solid", "99": "nonfrp", "100": "layer", "101": "flexible", "102": "coat", "103": "threshold", "104": "skirting", "105": "spring", "106": "ventilation", "107": "grooved", "108": "air", "109": "waterproofing", "110": "condiuts", "111": "knauf", "112": "glass", "113": "finishings", "114": "hinge", "115": "porcelain", "116": "floor", "117": "hardwood", "118": "plane", "119": "mep", "120": "diffuser", "121": "acoustic", "122": "fire", "123": "vibration", "124": "strucutral", "125": "lysaght", "126": "casting", "127": "grout", "128": "sprinkler", "129": "wool", "130": "track", "131": "amoured", "132": "bells", "133": "addings", "134": "isolators", "135": "assembly", "136": "toiletsink", "137": "board", "138": "concrete", "139": "promatect", "140": "pvc", "141": "overhead", "142": "swa", "143": "with", "144": "latches", "145": "welding", "146": "carbon", "147": "busbar", "148": "coated", "149": "smoke", "150": "toilet", "151": "upvc", "152": "pipes", "153": "handle", "154": "contains", "155": "surface", "156": "rockwool", "157": "cast", "158": "belongsto", "159": "painting", "160": "laminate", "161": "ceiling", "162": "door", "163": "galvanized", "164": "infill", "165": "rebar", "166": "ironmongery", "167": "laminates", "168": "cement", "169": "and", "170": "filter", "171": "bar", "172": "epoxy", "173": "core", "174": "noggins", "175": "at", "176": "fillet", "177": "mixture", "178": "fittings", "179": "none", "180": "pencil", "181": "fixing", "182": "reinforcement", "183": "cable", "184": "nonshrink", "185": "copper", "186": "spacer", "187": "rod", "188": "profile", "189": "weld", "190": "slab", "191": "pouring", "192": "angle", "193": "membrane", "194": "parttern", "195": "gemtree", "196": "insulation", "197": "cemenititious", "198": "alarm", "199": "protection", "200": "constrains"}, "task2id": {"board pretreatment and punching": 0, "2d panel assembly": 1, "butt weld and fillet weld": 2, "3d assembly": 3, "apply fire paint at strucutral member": 4, "rebar fixing": 5, "pouring concrete": 6, "door ironmongery and windows installation": 7, "door and window frame installation": 8, "installation of gypsum board at wall surface": 9, "installation of mep conduit at wall surface": 10, "stud installation at wall": 11, "rockwool infill and 2 layer of fire board installation at wall surface": 12, "stud installation at ceiling": 13, "rockwool infill and fire board installation at ceiling surface": 14, "layer and coat painting": 15, "installation of lighting": 16, "electrical cable wiring": 17, "installation of mep trunking at ceiling": 18, "installation of sprinkler pipes": 19, "window type ac installation": 20, "installation of vinyl floor and skirting": 21, "cabinets installation": 22}, "id2task": {"0": "board pretreatment and punching", "1": "2d panel assembly", "2": "butt weld and fillet weld", "3": "3d assembly", "4": "apply fire paint at strucutral member", "5": "rebar fixing", "6": "pouring concrete", "7": "door ironmongery and windows installation", "8": "door and window frame installation", "9": "installation of gypsum board at wall surface", "10": "installation of mep conduit at wall surface", "11": "stud installation at wall", "12": "rockwool infill and 2 layer of fire board installation at wall surface", "13": "stud installation at ceiling", "14": "rockwool infill and fire board installation at ceiling surface", "15": "layer and coat painting", "16": "installation of lighting", "17": "electrical cable wiring", "18": "installation of mep trunking at ceiling", "19": "installation of sprinkler pipes", "20": "window type ac installation", "21": "installation of vinyl floor and skirting", "22": "cabinets installation"}, "corpus": ["ac", "sink", "hboard", "cabinets", "closer", "sheet", "system", "electrode", "detector", "fm900", "member", "tv", "heads", "of", "coved", "doors", "corner", "paint", "electrical", "apply", "type", "2", "gypsum", "frp", "installation", "lighting", "wiring", "conduits", "homogeneous", "activated", "space", "flush", "firecut", "pretreatment", "lightings", "punching", "cladding", "battery", "frame", "cabinet", "3d", "filters", "panel", "couplings", "accessories", "for", "iron", "filler", "tiles", "emulsion", "tie", "runners", "2d", "purlins", "label", "butt", "skeleton", "windows", "trunking", "finsishes", "wire", "grilles", "tray", "antimould", "interface", "fan", "pipe", "channel", "timber", "conduit", "bondek", "chamber", "detectors", "corrugated", "elastometric", "metal", "weather", "shear", "beam", "rubber", "candleloc", "nonarmoured", "wall", "mineral", "composite", "window", "steel", "column", "vinyl", "nonslip", "tile", "aluminium", "room", "stud", "braces", "chair", "solid", "nonfrp", "layer", "flexible", "coat", "threshold", "skirting", "spring", "ventilation", "grooved", "air", "waterproofing", "condiuts", "knauf", "glass", "finishings", "hinge", "porcelain", "floor", "hardwood", "plane", "mep", "diffuser", "acoustic", "fire", "vibration", "strucutral", "lysaght", "casting", "grout", "sprinkler", "wool", "track", "amoured", "bells", "addings", "isolators", "assembly", "toiletsink", "board", "concrete", "promatect", "pvc", "overhead", "swa", "with", "latches", "welding", "carbon", "busbar", "coated", "smoke", "toilet", "upvc", "pipes", "handle", "contains", "surface", "rockwool", "cast", "belongsto", "painting", "laminate", "ceiling", "door", "galvanized", "infill", "rebar", "ironmongery", "laminates", "cement", "and", "filter", "bar", "epoxy", "core", "noggins", "at", "fillet", "mixture", "fittings", "none", "pencil", "fixing", "reinforcement", "cable", "nonshrink", "copper", "spacer", "rod", "profile", "weld", "slab", "pouring", "angle", "membrane", "parttern", "gemtree", "insulation", "cemenititious", "alarm", "protection", "constrains"]}